[
  {
    "Ref": "1ec09d88-e1c2-11e3-8c4a-0050568002cf",
    "SiteKey": "1",
    "Description": "Відділення №1 (до 30 кг): вул. Волонтерів, 16",
    "DescriptionRu": "Отделение №1 (до 30 кг): ул. Волонтеров, 16",
    "ShortAddress": "Ужгород, Волонтерів, 16",
    "Number": "1",
    "CityRef": "e221d627-391c-11dd-90d9-001a92567626",
    "CityDescription": "Ужгород",
    "SettlementRef": "e71f4773-4b33-11e4-ab6d-005056801329",
    "TypeOfWarehouse": "9a68df70-0267-42a8-bb5c-37f427e36ee4",
    "CategoryOfWarehouse": "Branch",
    "WarehouseStatus": "Working",
    "Longitude": "22.302113",
    "Latitude": "48.617410",
    "PlaceMaxWeightAllowed": "30",
    "TotalMaxWeightAllowed": "0",
    "ReceivingLimitationsOnDimensions": {"Width": 100, "Height": 100, "Length": 100},
    "SendingLimitationsOnDimensions": {"Width": 100, "Height": 100, "Length": 100}
  },
  {
    "Ref": "16006cee-e1c2-11e3-8c4a-0050568002cf",
    "SiteKey": "2",
    "Description": "Відділення №2 (вантажне): вул. Гагаріна, 101",
    "DescriptionRu": "Отделение №2 (грузовое): ул. Гагарина, 101",
    "ShortAddress": "Ужгород, Гагаріна, 101",
    "Number": "2",
    "CityRef": "e221d627-391c-11dd-90d9-001a92567626",
    "CityDescription": "Ужгород",
    "SettlementRef": "e71f4773-4b33-11e4-ab6d-005056801329",
    "TypeOfWarehouse": "841339c7-591a-42e2-8233-7a0a00f0ed6f",
    "CategoryOfWarehouse": "Branch",
    "WarehouseStatus": "Working",
    "Longitude": "22.283333",
    "Latitude": "48.633333",
    "PlaceMaxWeightAllowed": "1100",
    "TotalMaxWeightAllowed": "0",
    "ReceivingLimitationsOnDimensions": {"Width": 170, "Height": 190, "Length": 250},
    "SendingLimitationsOnDimensions": {"Width": 170, "Height": 190, "Length": 250}
  },
  {
    "Ref": "b1c4bdf9-3b98-11ed-a60f-48df37b921db",
    "SiteKey": "35001",
    "Description": "Поштомат №35001: вул. Собранецька, 145 (ТЦ)",
    "DescriptionRu": "Почтомат №35001: ул. Собранецкая, 145 (ТЦ)",
    "ShortAddress": "Ужгород, Собранецька, 145",
    "Number": "35001",
    "CityRef": "e221d627-391c-11dd-90d9-001a92567626",
    "CityDescription": "Ужгород",
    "SettlementRef": "e71f4773-4b33-11e4-ab6d-005056801329",
    "TypeOfWarehouse": "f9316480-5f2d-425d-bc2c-ac7cd29decf0",
    "CategoryOfWarehouse": "Postomat",
    "WarehouseStatus": "Working",
    "Longitude": "22.312000",
    "Latitude": "48.625000",
    "PlaceMaxWeightAllowed": "20",
    "TotalMaxWeightAllowed": "0",
    "ReceivingLimitationsOnDimensions": {"Width": 40, "Height": 30, "Length": 60},
    "SendingLimitationsOnDimensions": {"Width": 40, "Height": 30, "Length": 60}
  },
  {
    "Ref": "cc7a8bd2-b5f4-11ec-81bd-b8830365bd14",
    "SiteKey": "9001",
    "Description": "Пункт приймання-видачі (до 30 кг): вул. Мукачівська, 3",
    "DescriptionRu": "Пункт приема-выдачи (до 30 кг): ул. Мукачевская, 3",
    "ShortAddress": "Ужгород, Мукачівська, 3",
    "Number": "9001",
    "CityRef": "e221d627-391c-11dd-90d9-001a92567626",
    "CityDescription": "Ужгород",
    "SettlementRef": "e71f4773-4b33-11e4-ab6d-005056801329",
    "TypeOfWarehouse": "95dc212d-479c-4ffb-a8ab-8c1b9073d0bc",
    "CategoryOfWarehouse": "DropOff",
    "WarehouseStatus": "Working",
    "Longitude": "22.295000",
    "Latitude": "48.620000",
    "PlaceMaxWeightAllowed": "30",
    "TotalMaxWeightAllowed": "0",
    "ReceivingLimitationsOnDimensions": {"Width": 60, "Height": 60, "Length": 90}
  },
  {
    "Ref": "7b422fc3-e1c2-11e3-8c4a-0050568002cf",
    "SiteKey": "77",
    "Description": "Відділення №77 (ЗАКРИТЕ): пл. Корятовича, 1",
    "DescriptionRu": "Отделение №77 (ЗАКРЫТОЕ): пл. Корятовича, 1",
    "ShortAddress": "Ужгород, Корятовича, 1",
    "Number": "77",
    "CityRef": "e221d627-391c-11dd-90d9-001a92567626",
    "CityDescription": "Ужгород",
    "SettlementRef": "e71f4773-4b33-11e4-ab6d-005056801329",
    "TypeOfWarehouse": "9a68df70-0267-42a8-bb5c-37f427e36ee4",
    "CategoryOfWarehouse": "Branch",
    "WarehouseStatus": "Closed",
    "Longitude": "22.296000",
    "Latitude": "48.621000",
    "PlaceMaxWeightAllowed": "30",
    "TotalMaxWeightAllowed": "0",
    "ReceivingLimitationsOnDimensions": {"Width": 100, "Height": 100, "Length": 100}
  },
  {
    "Ref": "8d4cd0e9-4b64-11e4-a5f5-0025909b4a3c",
    "SiteKey": "1",
    "Description": "Відділення №1 (до 30 кг): вул. Пирогова, 19-А",
    "DescriptionRu": "Отделение №1 (до 30 кг): ул. Пирогова, 19-А",
    "ShortAddress": "Київ, Пирогова, 19-А",
    "Number": "1",
    "CityRef": "8d5a980d-391c-11dd-90d9-001a92567626",
    "CityDescription": "Київ",
    "SettlementRef": "e715719e-4b33-11e4-ab6d-005056801329",
    "TypeOfWarehouse": "9a68df70-0267-42a8-bb5c-37f427e36ee4",
    "CategoryOfWarehouse": "Branch",
    "WarehouseStatus": "Working",
    "Longitude": "30.505000",
    "Latitude": "50.447000",
    "PlaceMaxWeightAllowed": "30",
    "TotalMaxWeightAllowed": "0",
    "ReceivingLimitationsOnDimensions": {"Width": 100, "Height": 100, "Length": 100}
  },
  {
    "Ref": "1ec09d88-e1c2-11e3-8c4a-0050568002ff",
    "SiteKey": "101",
    "Description": "Відділення №101 (вантажне): просп. Перемоги, 67",
    "DescriptionRu": "Отделение №101 (грузовое): просп. Победы, 67",
    "ShortAddress": "Київ, Перемоги, 67",
    "Number": "101",
    "CityRef": "8d5a980d-391c-11dd-90d9-001a92567626",
    "CityDescription": "Київ",
    "SettlementRef": "e715719e-4b33-11e4-ab6d-005056801329",
    "TypeOfWarehouse": "841339c7-591a-42e2-8233-7a0a00f0ed6f",
    "CategoryOfWarehouse": "Branch",
    "WarehouseStatus": "Working",
    "Longitude": "30.430000",
    "Latitude": "50.455000",
    "PlaceMaxWeightAllowed": "1100",
    "TotalMaxWeightAllowed": "0"
  },
  {
    "Ref": "d1b5f0a4-3b98-11ed-a60f-48df37b921db",
    "SiteKey": "45123",
    "Description": "Поштомат №45123: вул. Хрещатик, 22",
    "DescriptionRu": "Почтомат №45123: ул. Крещатик, 22",
    "ShortAddress": "Київ, Хрещатик, 22",
    "Number": "45123",
    "CityRef": "8d5a980d-391c-11dd-90d9-001a92567626",
    "CityDescription": "Київ",
    "SettlementRef": "e715719e-4b33-11e4-ab6d-005056801329",
    "TypeOfWarehouse": "f9316480-5f2d-425d-bc2c-ac7cd29decf0",
    "CategoryOfWarehouse": "Postomat",
    "WarehouseStatus": "Working",
    "Longitude": "30.522000",
    "Latitude": "50.448000",
    "PlaceMaxWeightAllowed": "20",
    "TotalMaxWeightAllowed": "0",
    "ReceivingLimitationsOnDimensions": {"Width": 40, "Height": 30, "Length": 60}
  },
  {
    "Ref": "22cff3f2-e1c2-11e3-8c4a-0050568002cf",
    "SiteKey": "1",
    "Description": "Відділення №1 (до 30 кг): вул. Городоцька, 359",
    "DescriptionRu": "Отделение №1 (до 30 кг): ул. Городоцкая, 359",
    "ShortAddress": "Львів, Городоцька, 359",
    "Number": "1",
    "CityRef": "db5c88f0-391c-11dd-90d9-001a92567626",
    "CityDescription": "Львів",
    "SettlementRef": "e71c2a15-4b33-11e4-ab6d-005056801329",
    "TypeOfWarehouse": "9a68df70-0267-42a8-bb5c-37f427e36ee4",
    "CategoryOfWarehouse": "Branch",
    "WarehouseStatus": "Working",
    "Longitude": "23.973000",
    "Latitude": "49.828000",
    "PlaceMaxWeightAllowed": "30",
    "TotalMaxWeightAllowed": "0",
    "ReceivingLimitationsOnDimensions": {"Width": 100, "Height": 100, "Length": 100}
  },
  {
    "Ref": "3a1b7c55-e1c2-11e3-8c4a-0050568002cf",
    "SiteKey": "1",
    "Description": "Відділення №1 (вантажне): вул. Івана Франка, 2",
    "DescriptionRu": "Отделение №1 (грузовое): ул. Ивана Франко, 2",
    "ShortAddress": "Мукачево, Івана Франка, 2",
    "Number": "1",
    "CityRef": "e221d642-391c-11dd-90d9-001a92567626",
    "CityDescription": "Мукачево",
    "SettlementRef": "e71f4787-4b33-11e4-ab6d-005056801329",
    "TypeOfWarehouse": "841339c7-591a-42e2-8233-7a0a00f0ed6f",
    "CategoryOfWarehouse": "Branch",
    "WarehouseStatus": "Working",
    "Longitude": "22.716000",
    "Latitude": "48.443000",
    "PlaceMaxWeightAllowed": "1100",
    "TotalMaxWeightAllowed": "0",
    "ReceivingLimitationsOnDimensions": {"Width": 170, "Height": 190, "Length": 250}
  }
]
